rosemary_ai/__init__.py
rosemary_ai/_global_settings.py
rosemary_ai/_logger.py
rosemary_ai/decorators.py
rosemary_ai/exceptions.py
rosemary_ai/root.py
rosemary_ai/rosemary.py
rosemary_ai/_utils/__init__.py
rosemary_ai/_utils/dict_utils.py
rosemary_ai/_utils/file_utils.py
rosemary_ai/_utils/image.py
rosemary_ai/_utils/str_escape.py
rosemary_ai/_utils/str_utils.py
rosemary_ai/_utils/typing_utils.py
rosemary_ai/models/__init__.py
rosemary_ai/models/_model_info.py
rosemary_ai/models/_option_types.py
rosemary_ai/models/_utils.py
rosemary_ai/models/api_key_manager.py
rosemary_ai/models/claude_generator.py
rosemary_ai/models/cohere_generator.py
rosemary_ai/models/generator.py
rosemary_ai/models/generator_registry.py
rosemary_ai/models/gpt_generator.py
rosemary_ai/models/request_generator.py
rosemary_ai/models/stability_generator.py
rosemary_ai/multi_modal/__init__.py
rosemary_ai/multi_modal/image.py
rosemary_ai/parser/__init__.py
rosemary_ai/parser/_utils.py
rosemary_ai/parser/data_expression.py
rosemary_ai/parser/environment.py
rosemary_ai/parser/executor.py
rosemary_ai/parser/leaf_elements.py
rosemary_ai/parser/namespace.py
rosemary_ai/parser/rml_parser.py
rosemary_ai/parser/rosemary.lark
rosemary_ai/parser/transformer.py
rosemary_ai/parser/traverse.py
rosemary_ai/rml_common/_gpt.rml
rosemary_ai/rml_common/_http.rml
rosemary_ai/rml_common/_sd.rml
rosemary_ai/rml_common/_text.rml
rosemary_ai/rml_common/_utils.rml
rosemary_ai/rml_common/common.rml
rosemary_ai-0.0.19.dist-info/METADATA
rosemary_ai-0.0.19.dist-info/WHEEL
rosemary_ai-0.0.19.dist-info/licenses/LICENSE
rosemary_ai-0.0.19.dist-info/RECORD
