Metadata-Version: 2.3
Name: rosemary_ai
Version: 0.0.19
Summary: A Template Engine For LLMs and Generative AIs
Project-URL: Repository, https://github.com/snw2015/Rosemary-AI
Author-email: Samjna <snw201510@gmail.com>
License-File: LICENSE
Classifier: License :: OSI Approved :: MIT License
Classifier: Operating System :: OS Independent
Classifier: Programming Language :: Python :: 3
Requires-Python: >=3.10
Requires-Dist: anthropic
Requires-Dist: cohere
Requires-Dist: lark
Requires-Dist: openai
